LICENSE
MANIFEST.in
README.md
README_Dev.md
SimDefinitionTemplate.mapleaf
batchRunTemplate.mapleaf
pyproject.toml
requirements.txt
requirements_Dev.txt
setup.py
MAPLEAF/Main.py
MAPLEAF/Utilities.py
MAPLEAF/__init__.py
MAPLEAF.egg-info/PKG-INFO
MAPLEAF.egg-info/SOURCES.txt
MAPLEAF.egg-info/dependency_links.txt
MAPLEAF.egg-info/entry_points.txt
MAPLEAF.egg-info/not-zip-safe
MAPLEAF.egg-info/requires.txt
MAPLEAF.egg-info/top_level.txt
MAPLEAF/IO/CythonLog.c
MAPLEAF/Motion/CythonAngularVelocity.c
MAPLEAF/Motion/CythonQuaternion.c
MAPLEAF/Motion/CythonVector.c
MAPLEAF/Rocket/CythonFinFunctions.cpp
MAPLEAF/ENV/AtmosphereModelling.py
MAPLEAF/ENV/EarthModelling.py
MAPLEAF/ENV/MeanWindModelling.py
MAPLEAF/ENV/TurbulenceModelling.py
MAPLEAF/ENV/US_STANDARD_ATMOSPHERE.txt
MAPLEAF/ENV/__init__.py
MAPLEAF/ENV/environment.py
MAPLEAF/ENV/launchRail.py
MAPLEAF/ENV/sphericalHarmonicGravityCoeffs.txt
MAPLEAF/Examples/BatchSims/CanardOptimizationTest.mapleaf
MAPLEAF/Examples/BatchSims/NASAVerificationCases.mapleaf
MAPLEAF/Examples/BatchSims/OpenRocketCases.mapleaf
MAPLEAF/Examples/BatchSims/ParametricFinBodyCases.mapleaf
MAPLEAF/Examples/BatchSims/SooyAP98DC97Cases.mapleaf
MAPLEAF/Examples/BatchSims/SparrowCases.mapleaf
MAPLEAF/Examples/BatchSims/StaticStabilityCases.mapleaf
MAPLEAF/Examples/BatchSims/regressionTests.mapleaf
MAPLEAF/Examples/Motors/B4-4.txt
MAPLEAF/Examples/Motors/C6-3.txt
MAPLEAF/Examples/Motors/Empty.txt
MAPLEAF/Examples/Motors/J115.txt
MAPLEAF/Examples/Motors/NASAStage1Motor.txt
MAPLEAF/Examples/Motors/NASAStage2Motor.txt
MAPLEAF/Examples/Motors/test.txt
MAPLEAF/Examples/Motors/test2.txt
MAPLEAF/Examples/Simulations/AdaptTimeStep.mapleaf
MAPLEAF/Examples/Simulations/Canards.mapleaf
MAPLEAF/Examples/Simulations/CanardsOptimization.mapleaf
MAPLEAF/Examples/Simulations/CanardsOptimization_continue.mapleaf
MAPLEAF/Examples/Simulations/ConvergenceTest.mapleaf
MAPLEAF/Examples/Simulations/EventDetector.mapleaf
MAPLEAF/Examples/Simulations/FixedForce.mapleaf
MAPLEAF/Examples/Simulations/Haisunaata.mapleaf
MAPLEAF/Examples/Simulations/InitializedOptimization.mapleaf
MAPLEAF/Examples/Simulations/IntermediateAxisTheorem.mapleaf
MAPLEAF/Examples/Simulations/Jake1.mapleaf
