Metadata-Version: 2.1
Name: MAPLEAF
Version: 0.8.16
Summary: A compact, extensible rocket flight simulation framework for researchers and rocket designers
Home-page: https://github.com/henrystoldt/MAPLEAF
Author: Henry Stoldt
Author-email: hhstoldt@ucalgary.ca
License: MIT
Platform: UNKNOWN
Classifier: Programming Language :: Python :: 3
Classifier: License :: OSI Approved :: MIT License
Classifier: Operating System :: OS Independent
Classifier: Development Status :: 4 - Beta
Classifier: Intended Audience :: Science/Research
Classifier: Intended Audience :: Developers
Classifier: Programming Language :: Python :: 3
Classifier: Programming Language :: Python :: 3.6
Classifier: Programming Language :: Python :: 3.7
Classifier: Programming Language :: Python :: 3.8
Classifier: Natural Language :: English
Classifier: Topic :: Scientific/Engineering :: Physics
Requires-Python: >=3.6
